README.rst
setup.py
fmapi/__init__.py
fmapi/test.py
fmapi.egg-info/PKG-INFO
fmapi.egg-info/SOURCES.txt
fmapi.egg-info/dependency_links.txt
fmapi.egg-info/not-zip-safe
fmapi.egg-info/top_level.txt