Metadata-Version: 1.0
Name: fmapi
Version: 0.3
Summary: Foundation Mercury Python API Client
Home-page: https://github.com/FoundationMercury/fmpyapi
Author: Foundation Mercury
Author-email: info@foundationmercury.com
License: MIT
Platform: UNKNOWN
